compas_fab/__init__.py
compas_fab/__main__.py
compas_fab/__version__.py
compas_fab/backends/__init__.py
compas_fab/backends/exceptions.py
compas_fab/backends/tasks.py
compas_fab/backends/interfaces/__init__.py
compas_fab/backends/interfaces/backend_features.py
compas_fab/backends/interfaces/client.py
compas_fab/backends/kinematics/__init__.py
compas_fab/backends/kinematics/analytical_inverse_kinematics.py
compas_fab/backends/kinematics/analytical_plan_cartesian_motion.py
compas_fab/backends/kinematics/exceptions.py
compas_fab/backends/kinematics/utils.py
compas_fab/backends/kinematics/solvers/__init__.py
compas_fab/backends/kinematics/solvers/offset_wrist.py
compas_fab/backends/kinematics/solvers/offset_wrist_kinematics.py
compas_fab/backends/kinematics/solvers/spherical_wrist.py
compas_fab/backends/kinematics/solvers/spherical_wrist_kinematics.py
compas_fab/backends/pybullet/__init__.py
compas_fab/backends/pybullet/client.py
compas_fab/backends/pybullet/const.py
compas_fab/backends/pybullet/conversions.py
compas_fab/backends/pybullet/exceptions.py
compas_fab/backends/pybullet/planner.py
compas_fab/backends/pybullet/utils.py
compas_fab/backends/pybullet/backend_features/__init__.py
compas_fab/backends/pybullet/backend_features/pybullet_add_attached_collision_mesh.py
compas_fab/backends/pybullet/backend_features/pybullet_add_collision_mesh.py
compas_fab/backends/pybullet/backend_features/pybullet_append_collision_mesh.py
compas_fab/backends/pybullet/backend_features/pybullet_forward_kinematics.py
compas_fab/backends/pybullet/backend_features/pybullet_inverse_kinematics.py
compas_fab/backends/pybullet/backend_features/pybullet_remove_attached_collision_mesh.py
compas_fab/backends/pybullet/backend_features/pybullet_remove_collision_mesh.py
compas_fab/backends/ros/__init__.py
compas_fab/backends/ros/client.py
compas_fab/backends/ros/direct_ur_action_client.py
compas_fab/backends/ros/exceptions.py
compas_fab/backends/ros/fileserver_loader.py
compas_fab-1.1.4.dist-info/licenses/AUTHORS.rst
compas_fab-1.1.4.dist-info/licenses/LICENSE
compas_fab-1.1.4.dist-info/METADATA
compas_fab-1.1.4.dist-info/WHEEL
compas_fab-1.1.4.dist-info/top_level.txt
compas_fab-1.1.4.dist-info/RECORD
