Metadata-Version: 2.4
Name: compas_fab
Version: 1.1.4
Summary: Robotic fabrication package for the COMPAS Framework that facilitates the planning and execution of robotic fabrication processes.
Home-page: https://github.com/compas-dev/compas_fab
Author: Gramazio Kohler Research
Author-email: Romana Rust <rust@arch.ethz.ch>, Gonzalo Casas <casas@arch.ethz.ch>, Stefana Parascho <parascho@arch.ethz.ch>, David Jenny <jenny@arch.ethz.ch>, Kathrin Dörfler <doerfler@arch.ethz.ch>, Matthias Helmreich <helmreich@arch.ethz.ch>, Augusto Gandia <gandia@arch.ethz.ch>, Zhao Ma <ma@arch.ethz.ch>, Inés Ariza <ariza@arch.ethz.ch>, Matteo Pacher <pacher@arch.ethz.ch>, Beverly Lytle <lytle@arch.ethz.ch>, Yijiang Huang <yijiangh@mit.edu>, Chen Kasirer <kasirer@arch.ethz.ch>, Edvard Bruun 
License: MIT License
Project-URL: Homepage, https://compas.dev/compas_fab/latest
Project-URL: Repository, https://github.com/compas-dev/compas_fab
Classifier: Development Status :: 4 - Beta
Classifier: Topic :: Scientific/Engineering
Classifier: Programming Language :: Python
Classifier: Programming Language :: Python :: 3
Classifier: Programming Language :: Python :: 3.9
Classifier: Programming Language :: Python :: 3.10
Classifier: Programming Language :: Python :: 3.11
Requires-Python: >=3.9
License-File: LICENSE
License-File: AUTHORS.rst
Requires-Dist: compas<3,>=2.0.4
Requires-Dist: compas_robots<1,>=0.3
Requires-Dist: roslibpy<2,>=1.1
Requires-Dist: pyserial
Provides-Extra: dev
Requires-Dist: pybullet; extra == "dev"
Requires-Dist: attrs>=19.3.0; extra == "dev"
Requires-Dist: black; extra == "dev"
Requires-Dist: bump2version>=1.0.1; extra == "dev"
Requires-Dist: check-manifest>=0.36; extra == "dev"
Requires-Dist: compas-invocations2; extra == "dev"
Requires-Dist: ruff; extra == "dev"
Requires-Dist: importlib_metadata<5.0; extra == "dev"
Requires-Dist: invoke>=0.14; extra == "dev"
Requires-Dist: pythonnet; extra == "dev"
Requires-Dist: pytest; extra == "dev"
Requires-Dist: pytest_mock; extra == "dev"
Requires-Dist: pytest-cov; extra == "dev"
Requires-Dist: sphinx_compas2_theme; extra == "dev"
Requires-Dist: sybil~=8.0.1; extra == "dev"
Requires-Dist: twine; extra == "dev"
Requires-Dist: tomlkit; extra == "dev"
Dynamic: author
Dynamic: home-page
Dynamic: license-file
